pytest_terraform/__init__.py
pytest_terraform/exceptions.py
pytest_terraform/hooks.py
pytest_terraform/lock.py
pytest_terraform/options.py
pytest_terraform/plugin.py
pytest_terraform/tf.py
pytest_terraform/xdist.py
pytest_terraform-0.7.0.dist-info/METADATA
pytest_terraform-0.7.0.dist-info/WHEEL
pytest_terraform-0.7.0.dist-info/entry_points.txt
pytest_terraform-0.7.0.dist-info/RECORD
