Metadata-Version: 2.1
Name: pytest-terraform
Version: 0.7.0
Summary: A pytest plugin for using terraform fixtures
Home-page: https://github.com/cloud-custodian/pytest-terraform
License: Apache-2.0
Author: Kapil Thangavelu
Author-email: kapilt@gmail.com
Requires-Python: >=3.7,<4.0
Classifier: License :: OSI Approved :: Apache Software License
Classifier: Programming Language :: Python :: 3
Classifier: Programming Language :: Python :: 3.7
Classifier: Programming Language :: Python :: 3.8
Classifier: Programming Language :: Python :: 3.9
Classifier: Programming Language :: Python :: 3.10
Classifier: Programming Language :: Python :: 3.11
Classifier: Programming Language :: Python :: 3.12
Classifier: Topic :: Software Development :: Testing
Classifier: Topic :: System :: Distributed Computing
Classifier: Topic :: System :: Systems Administration
Requires-Dist: jmespath (>=0.10.0)
Requires-Dist: portalocker (>=1.7.0)
Requires-Dist: pytest (>=6.0)
Requires-Dist: pytest-xdist (>=1.31.0)
Project-URL: Repository, https://github.com/cloud-custodian/pytest-terraform
